apus/__init__.py
apus/apus.py
apus/cli.py
apus/hello.py
apus/menu.py
apus/config/__init__.py
apus/config/db.py
apus/config/settings.py
apus/fluent_python/__init__.py
apus/fluent_python/ex1.1.py
apus/users/__init__.py
apus/users/models.py
apus-0.1.10.dist-info/DESCRIPTION.rst
apus-0.1.10.dist-info/METADATA
apus-0.1.10.dist-info/RECORD
apus-0.1.10.dist-info/WHEEL
apus-0.1.10.dist-info/entry_points.txt
apus-0.1.10.dist-info/metadata.json
apus-0.1.10.dist-info/top_level.txt
