Metadata-Version: 2.0
Name: apus
Version: 0.1.10
Summary: Caso de estudo para criação de Python Package.
Home-page: https://github.com/geislor/apus
Author: Geislor Crestani
Author-email: geislor@gmail.com
License: MIT license
Keywords: apus
Platform: UNKNOWN
Classifier: Development Status :: 2 - Pre-Alpha
Classifier: Intended Audience :: Developers
Classifier: License :: OSI Approved :: MIT License
Classifier: Natural Language :: English
Classifier: Programming Language :: Python :: 2
Classifier: Programming Language :: Python :: 2.6
Classifier: Programming Language :: Python :: 2.7
Classifier: Programming Language :: Python :: 3
Classifier: Programming Language :: Python :: 3.3
Classifier: Programming Language :: Python :: 3.4
Classifier: Programming Language :: Python :: 3.5
Requires-Dist: Click (>=6.0)
Requires-Dist: sqlalchemy (==1.0.13)
